{"5LE5gNcIxvYYA4J7+vqOHA==":"logo-96x30.png","y4QgxALJXUT5XanCnjLXOQ==":"logo-1-96x30.png","K1T/1ZB7d9m/IG680Gp9/A==":"logo-344x108.png","7t/4/8WQ+LJg/5agyIa6Ww==":"1.webp","jF3s9yN2uvyRxui319qtAA==":"2.webp","WUO04MWqr45ixKnMf0hX8A==":"1-1.webp","nMWfX96+uhQqfpJC0T2QmQ==":"3.webp","3jwmqxzeJoKTo5UtJjooEQ==":"2-1.webp","IMY+fnAmd0aeveBlsK7tlg==":"4.webp","Gx2XlwTxhA1yjywQEpVCDQ==":"5.webp","bOMpn48i61OlhVE17wKpmg==":"5-1.webp","qol0v2yVXYw9YL1syDxQtw==":"6.webp","eGHkJs/kltunwCSEtRaAsQ==":"6-1.webp","gW+E2As2ymF8BICAKnfmuA==":"7.webp","0ifacOMCDGScy2hblqwazw==":"8.webp","sA+Rfdbrvk2nyhYiQVp4RQ==":"9.webp","FW0VDTa0Md2upR1o4HzcLQ==":"7-1.webp","LGvp38pweKVnTWbVqVspSA==":"8-1.webp","Rn6NN0WU/QWUA1icqYVL9Q==":"9-1.webp","MOTI/MNdMz6ls3UVczn+2A==":"logo-2-96x30.png","cjDEZEwyPxluN0GRaVvAHw==":"tb15wglwbr0gk0jszfnxxbrrxxa-150x150.png","7qXRB082yY5MFdxbqlsoTw==":"11.webp","Vlq7I5zVIcJC0GMWwtAthQ==":"81ab3f69-2391-4129-88d7-d285aa0ffd93_vn-276-260.png_580x580q80.png_.webp","zIKbuIbeGtJyhqQnORXBJw==":"mbr-1920x1248.png","yXKbOk+ieOTF83iYiw2lww==":"mbr-1920x1080.jpg","hq1YI8Vm/aT+zKaWgaiZJA==":"d%E1%BA%A7u%20g%E1%BB%99i%201.webp","6Sa/5bhUGx6kZ9NDQEVfMg==":"cat%20foods%201.webp","5gegPC9k5gZUOfUoVgiaEA==":"h%C3%B4p%20s%E1%BB%AFa%201.webp","CmBX/pGRn5onRqoaz4rGpA==":"x%E1%BB%8Bt%20m%C3%B9i%201.webp","Cr+eg66r6PRVNVyq4OtYcg==":"cf60890e4305b2e0e0343ce7f2bd7594.jpg_720x720q80.jpg_.webp","mHORW0ykdG8H6CquiAAlBA==":"background4.jpg","Cesjxe6cW0NYFSAP4kiRig==":"features1.jpg","703jGkvtoXpxbZTG7S89UA==":"features2.jpg","WeIcOp+qLfFEPxVAXUUAEA==":"features4.jpg","Vb7GgbMoe0curpGYBParsg==":"background3.jpg","jv1Oocv/EhS1XeW8Vo4DNg==":"giay.webp","WvrVAAqDOCpLuNlJ0Gp7Ow==":"daudua.webp","32qaFPJKuqtVXQytTmFKvw==":"sach.webp","IWsYaCcfaNjMExSjwsQelQ==":"yensao.webp","+/sWTDtVuxhvbES4N30aJQ==":"lochinhanh.webp","igT3wC2i8vHnrL0XSCCAtA==":"cafferang.webp","tCuz0pwcR6C8jjj3c5jQWA==":"onghut.webp","5ghAYLmKtvgpz0t3tdGoXw==":"mask.webp","xN+XzPs4kMj6159evaxYOg==":"matong.webp","0QGTDc2O/mWgHoNLA4gaFQ==":"chotkoday.webp","ncB5t+K2Mc7U0OQhD69k4g==":"book.webp","gbronfvbgrhi5gcmVNJq/A==":"daynit.webp","h7eKlOK8Q+GOfPrIM6peog==":"pho.webp","JZEwKOsRhmKk7d1jnTHO/A==":"3-1.webp","7YFbhiTNQG1GMRpEfIbEKw==":"4-1.webp","kJkWVkQrPC4S8LAcxW/7LA==":"3-2.webp","hu62WtI1ui57KzeRBMXAYg==":"10.webp","SsvLZbPQdUgAl6vbZ7qB7g==":"14.webp","R2C7wSQlF9n0j6GHvbZZTg==":"17.webp","uGigop1LmG0g0kBexcy5rA==":"12.webp","wY14x9b8+tyv45VXqA5Saw==":"14-1.webp","CP3w2I0aLrgtjFSaHx4uGQ==":"logo-1-344x108.png","JyAfYcPQvfDJHvGBUvhVzA==":"hatmix.webp","uJH20rKVbpXNZJ4hZyKJ2w==":"xitmoctoc.webp","IcaDIg85PWZ+BKmPKvD3tA==":"logo-166x52.png","RMpaH2Vvg0AGnWL5vqLkRg==":"logo-1-166x52.png","opFGX+Nh4biBjXLDtLpsvg==":"balo.webp","kk1+NEjpQyP2qia+cLk6Nw==":"hatchia.webp","hSbouiE05DgEQxwlAfl+WA==":"vali.webp","RICr+mAeflvuNg1fH0C3Yw==":"bsv.webp","ApXPtEKPkrjArRK0gpU0ug==":"sugar.webp","G6lg3KMx3f5ULHLKZc6Dsg==":"giaydf.webp","o/Gl0VJEXExJkjDJYJq1sQ==":"screenshot-1730952286858-1336x314.png","oyRXmL0yN3Z+/dHYDaQXUw==":"1-2.webp","Kdi0Oe0wExJfOmihbIePmg==":"2-2.webp","cRme04tQSj+9w/CtnQqtdg==":"3-1200x628.png","6RIka9QGTTBi7/6hVFwMIA==":"3-1-1200x628.png","itsy4nzcQPtJ9wpcsfgfQg==":"xiao1.webp","eSmELbFjKySDM6jAMSTkdQ==":"xiao2.webp","YkOb+nU0tSzq2BDlT0zdOA==":"xiao2-1.webp","e4ZOBq2v1gmnk+NZ0nHl7A==":"xiao3.webp","1q8fyTPmsWWT/0YzVUMOMw==":"xiao4.webp","S+EUtjfyChN2i18uiwY1zw==":"xiao5.webp","6qlgze3gDZIXPf1W6im31A==":"xiao6.webp","911X7bM4yT2Mobv6BsMc+g==":"background8.jpg","Ql5cS6ajQkLC1paSQqGpsg==":"xiao7.webp","/Wo+erPqbaYLgox8uZSKyg==":"xiao8.webp","b2xdrUFvo20odCjncjbOAg==":"vivo1.webp","Yksg3N4p3crFH9v5rBSSBQ==":"vivo2.webp","7GdsDdjihPGOimtwEuK6kQ==":"vivo3.webp","hJswzahybbzEJj6j/IIwxA==":"vivo4.webp","5XOs4xVGtfJv+GqMadxlpg==":"vivo5.webp","KOqFhn1vlrBA9nRYopATag==":"vivo6.webp","aYXzFQdJ81huDATBG855BA==":"vivo7.webp","i3Rq9wRKkYNrCMzXmCKhgQ==":"vivo8.webp","eGut4b10+fmMFyKLg9V9EA==":"ggl1.webp","ag4Jt6paT3V3ewvKfCvrkA==":"ggl2.webp","CObbvSmVHg+EjY7/oHhkjQ==":"ggl3.webp","JdBsZIPAAt07lBpWfPTx2Q==":"ggl4.webp","xzvaaiKdm7nOEm0xSU6N9g==":"ggl5.webp","HIX25xtS/e9BSJQvNekhMQ==":"ggl6.webp","8L2zVPAuVkCM5jIexdykxA==":"ggl7.webp","+Jp4vGzUBh3nQc0XIvk53w==":"ggl8.webp","ee1f/xLdvdyFucPSl1RxJg==":"ggl-240x135.png","kpQA47sHI+9tZ60tFcJ5Gw==":"vivo-225x225.png","fiYCXjSVGs8cyztWzo+3pA==":"laphp.webp","qKboxUn1uV7AqDHtcVKDdw==":"laphp1.webp","UQXbYuQPuBsi+YZCyfEaiQ==":"laphp2.webp","wsA1z/SNX/FkHW8n2krqng==":"laphp3.webp","ypzcnJdN+8/SzmAbSPqwEQ==":"laphp4.webp","F2qGHrmu7AIJTA8WiFQRCQ==":"laphp5.webp","b3MdQWxovG2Z/eQM7kGmjg==":"laphp5-1.webp","1qCqVbo3bWVQLTvf+BzLlA==":"laphp5-2.webp","uBjVtBN2m2J4kSJHkQkrVA==":"laphp5-3.webp","LZloibuSD6hRxgRCb1CkBA==":"laphp6.webp","bpPB9MqClQ4iFMhmtVtrZw==":"laphp7.webp","mUWgjcPwnh1X/vWleR8Tug==":"laphp6-1.webp","CN2B7305FRs6uXJNwRQVKw==":"laphp-1.webp","Smx7+lPe3HzsIzQOmrzcJw==":"laphp1-1.webp","zHLq5XijZ3M+gOb0cw8QKg==":"laphp1-2.webp","WLYaAHx5UuBSz4mYS+oG9w==":"laphp2-1.webp","Pr1KxVNNiKKrVOpxbSg0Ew==":"laphp3-1.webp","yxgvbeIA/V5yFOsppKZxcA==":"lapmsi1.webp","1bj9X9rcuu1e2apBT0S0kg==":"mapmsi2.webp","Y7r+i4xHTODE88fOiQ6AxQ==":"lapmsi2.webp","Jzc969lg2jiRED/lkHnxZQ==":"lapmsi4.webp","MPj5UiP8+yM3qtcxE4xurQ==":"lapmsi3.webp","LZ40JKOysdvPNgOdQe2sbg==":"lapmsi5.webp","JD6bZtTsAXaNYkRg11JH9A==":"lapmsi6.webp","kAsU91rZao8mqMBthY701w==":"acer1.webp","Nd9QrhJFPcSJXvVNNWoNGQ==":"acer2.webp","GWqxvH42rVnzS6nEwNtHTA==":"acer3.webp","+7kZSlSEtdiOhkmklnvJig==":"acer4.webp","51s9IbPyorsYxv5r80zpuA==":"acer5.webp","cDF/PwyOvViIQ8QKPjsK0Q==":"acer5-1.webp","+q1RPXcw7flXVV0YF1kv6A==":"acer4-1.webp","c0iSnNdFQRr9C4OnMpQPYA==":"acer4-2.webp","anXRGZ7+6xvOnL4ZTowecQ==":"acer5-2.webp","HcqN0jjYu7u/ZyBM4LtCXg==":"acer6.webp","Op9zM+QjR0MIRZ2jDs4knA==":"acer7.webp","18rfSU/+R1VA7ynWzqca7g==":"acer8.webp","AV/vmwHlK7ZaRu0gf9GItg==":"cam1.webp","uHA+lXhv3DDsBn9d499buw==":"mbr-506x506.jpg"}